{
  "interactionModel": {
    "dialog": {
      "intents": [
        {
          "slots": [
            {
              "name": "CatchAll",
              "elicitationRequired": true,
              "type": "AMAZON.SearchQuery",
              "confirmationRequired": false,
              "prompts": {
                "elicitation": "Elicit.Slot.293431082439.1092679286774"
              }
            }
          ],
          "name": "HelloWorldIntent",
          "confirmationRequired": false,
          "prompts": {}
        }
      ],
      "delegationStrategy": "ALWAYS"
    },
    "languageModel": {
      "intents": [
        {
          "name": "AMAZON.CancelIntent",
          "samples": []
        },
        {
          "name": "AMAZON.HelpIntent",
          "samples": []
        },
        {
          "name": "AMAZON.StopIntent",
          "samples": []
        },
        {
          "slots": [
            {
              "name": "CatchAll",
              "type": "AMAZON.SearchQuery",
              "samples": [
                "{CatchAll}"
              ]
            }
          ],
          "name": "HelloWorldIntent",
          "samples": [
            "hello",
            "how are you",
            "say hi world",
            "say hi",
            "hi",
            "say hello world",
            "say hello"
          ]
        },
        {
          "name": "AMAZON.NavigateHomeIntent",
          "samples": []
        },
        {
          "name": "AMAZON.FallbackIntent",
          "samples": []
        }
      ],
      "types": [],
      "invocationName": "Sassy me"
    },
    "prompts": [
      {
        "variations": [
          {
            "type": "PlainText",
            "value": "what do you want?"
          }
        ],
        "id": "Elicit.Slot.293431082439.1092679286774"
      }
    ]
  }
}